{
    "date": "2024.3.18 (Mon)",
    "u": "なにわ自転車道 🚲 神崎川左岸",
    "strong": "Naniwa Cycling Load<br><small>(the left bank of Kanzakigawa)</small>",
    "readme": "README.md",
    "url": "naniwa-cycling-load/?id=kanzakigawa",
    "youtube": "zUF-oI-MHHk",
    "directory": "https://ia600207.us.archive.org/1/items/naniwa-cycling-load/",
    "cover": "naniwa-cycling-load.thumbs/kanzakigawa/006_000177.jpg",
    "video": [
        {
            "title": "大阪­広域環境施­設組合",
            "src": "kanzakigawa/001.ia.mp4",
            "track": "kanzakigawa/001.vtt"
        },
        {
            "title": "阪急京都線・千里線",
            "src": "kanzakigawa/002.ia.mp4",
            "track": "kanzakigawa/002.vtt"
        },
        {
            "title": "JRおおさか東線・京都線",
            "src": "kanzakigawa/003.ia.mp4",
            "track": "kanzakigawa/003.vtt"
        },
        {
            "title": "十八条大橋 ~ 三國橋",
            "src": "kanzakigawa/004.ia.mp4",
            "track": "kanzakigawa/004.vtt"
        },
        {
            "title": "新三国橋 ~ 神洲橋 ~ 大豊橋",
            "src": "kanzakigawa/005.ia.mp4",
            "track": "kanzakigawa/005.vtt"
        },
        {
            "title": "淀川区加島",
            "src": "kanzakigawa/006.ia.mp4",
            "track": "kanzakigawa/006.vtt"
        }
    ],
    "link": [
        {
            "text": "なにわ自転車道 🚲 Naniwa Cycling Load",
            "url": "../naniwa-cycling-load/",
            "target": "_self"
        },
        {
            "text": "東淀工場 - 大阪­広域環境施­設組合",
            "url": "https://www.osaka-env-paa.jp/kojo/higashiyodo/index.html",
            "target": "_blank"
        },
        {
            "text": "阪急レンタサイクル営業場所 | 上新庄駐輪センターはこべ館・三国北駐輪センター",
            "url": "https://www.hankyu.co.jp/station/service/rental02.html",
            "target": "_blank"
        },
        {
            "text": "レンタサイクル 駅リンくん 新大阪店",
            "url": "https://www.ekiren.com/ekirinkun",
            "target": "_blank"
        }
    ]
}